themis.finals-1.0.0-py2.7-nspkg.pth
themis/finals/__about__.py
themis/finals/__init__.py
themis/finals/capsule_api.py
themis/finals/flag_api.py
themis.finals-1.0.0.dist-info/METADATA
themis.finals-1.0.0.dist-info/RECORD
themis.finals-1.0.0.dist-info/WHEEL
themis.finals-1.0.0.dist-info/entry_points.txt
themis.finals-1.0.0.dist-info/namespace_packages.txt
themis.finals-1.0.0.dist-info/top_level.txt
