Metadata-Version: 2.1
Name: themis.finals
Version: 1.0.0
Summary: Themis Finals CLI & public API library
Home-page: https://github.com/themis-project/themis-finals-py
Author: Alexander Pyatkin
Author-email: aspyatkin@gmail.com
License: MIT
Platform: UNKNOWN
Requires-Dist: setuptools (>=35.0.0)
Requires-Dist: requests (>=2.18.4)
Requires-Dist: grequests (==0.3.0)
Requires-Dist: click (>=6.7)
Requires-Dist: python-dateutil (>=2.6.0)
Requires-Dist: PyJWT (<1.7.0,>=1.6.4)
Requires-Dist: cryptography (<2.3.0,>=2.2.2)
Requires-Dist: enum34 (>=1.1.6); python_version<"3.4"
